[
    {
        "question": "<span>The ratio of boys to girls initial in a college is 5 : 6. If 40 boys leave the college and 50 girls join the college, the ratio will become 8 : 11. Find the number of girls (initial) in the college.</span>",
        "option_1": "<span style=\"color:#4224e9\"> 720</span>",
        "option_2": "<span style=\"color:#4224e9\"> 860</span>",
        "option_3": "<span style=\"color:#4224e9\"> 640</span>",
        "option_4": "<span style=\"color:#4224e9\"> 740</span>",
        "option_5": "",
        "answer": "1",
        "solution": "<br>https://appx-content-v2.classx.co.in/website/bulk_uploader_images/1750330267389_image001.png"
    },
    {
        "question": "<span>If a ∶ b = c ∶ d = e ∶ f = 5 ∶ 7, then what is the ratio (3a + 5c + 11e) ∶ (3b + 5d + 11f)?</span>",
        "option_1": "<span style=\"color:#4224e9\"> 11 : 7</span>",
        "option_2": "<span style=\"color:#4224e9\"> 5 : 7</span>",
        "option_3": "<span style=\"color:#4224e9\"> 3 : 7</span>",
        "option_4": "<span style=\"color:#4224e9\"> 7 : 11</span>",
        "option_5": "",
        "answer": "2",
        "solution": "<br>https://appx-content-v2.classx.co.in/website/bulk_uploader_images/1750330267389_image002.png"
    },
    {
        "question": "<span>In a company, the ratio of men and women is 5 : 3, respectively. When 150 additional women are employed in the company, the ratio becomes 5 : 4. How many men are employed in the company?</span>",
        "option_1": "<span style=\"color:#4224e9\"> 850</span>",
        "option_2": "<span style=\"color:#4224e9\"> 550</span>",
        "option_3": "<span style=\"color:#4224e9\"> 950</span>",
        "option_4": "<span style=\"color:#4224e9\"> 750</span>",
        "option_5": "",
        "answer": "4",
        "solution": "<br>https://appx-content-v2.classx.co.in/website/bulk_uploader_images/1750330267389_image003.png"
    },
    {
        "question": "<span>A sum of money is divided among P, Q, R and S in the proportion of 4 : 9 : 2 : 3. If Q gets ₹560 more than R, then the share of S is:</span>",
        "option_1": "<span style=\"color:#4224e9\"> ₹340</span>",
        "option_2": "<span style=\"color:#4224e9\"> ₹240</span>",
        "option_3": "<span style=\"color:#4224e9\"> ₹440</span>",
        "option_4": "<span style=\"color:#4224e9\"> ₹140</span>",
        "option_5": "",
        "answer": "2",
        "solution": "<br>https://appx-content-v2.classx.co.in/website/bulk_uploader_images/1750330267389_image004.png"
    },
    {
        "question": "<span>If A:B = 6 : 8 and B:C = 7 : 12, then A:B:C is:</span>",
        "option_1": "<span style=\"color:#4224e9\"> 21:32:40</span>",
        "option_2": "<span style=\"color:#4224e9\"> 14:31:20</span>",
        "option_3": "<span style=\"color:#4224e9\"> 11:23:40</span>",
        "option_4": "<span style=\"color:#4224e9\"> 21:28:48</span>",
        "option_5": "",
        "answer": "4",
        "solution": "<br>https://appx-content-v2.classx.co.in/website/bulk_uploader_images/1750330267389_image005.png"
    },
    {
        "question": "<span>If A:B = 6 : 8 and B:C = 7 : 10, then A:B:C is:</span>",
        "option_1": "<span style=\"color:#4224e9\"> 21:23:40</span>",
        "option_2": "<span style=\"color:#4224e9\"> 23:32:40</span>",
        "option_3": "<span style=\"color:#4224e9\"> 14:31:20</span>",
        "option_4": "<span style=\"color:#4224e9\"> 21:28:40</span>",
        "option_5": "",
        "answer": "4",
        "solution": "<br>https://appx-content-v2.classx.co.in/website/bulk_uploader_images/1750330267389_image006.png"
    },
    {
        "question": "<span>The cost of a diamond varies directly as the square of its weight. Once, this diamond broke into four pieces with weights in the ratio of 4 : 3 : 2 : 1 .When the pieces were sold, the merchant got ₹63,000 less than that of one piece. Find the original price of the diamond.</span>",
        "option_1": "<span style=\"color:#4224e9\"> ₹80,000</span>",
        "option_2": "<span style=\"color:#4224e9\"> ₹86,000</span>",
        "option_3": "<span style=\"color:#4224e9\"> ₹90,000</span>",
        "option_4": "<span style=\"color:#4224e9\"> ₹75,000</span>",
        "option_5": "",
        "answer": "3",
        "solution": "<br>https://appx-content-v2.classx.co.in/website/bulk_uploader_images/1750330267389_image007.png"
    },
    {
        "question": "<span>In a collection of rare coins, there is one gold coin for every four non-gold coins. If 20 more gold coins are added to the collection, the ratio of the number of gold coins to that of non-gold coins will be 2:3. The total number of coins in the collection will now become ________.</span>",
        "option_1": "<span style=\"color:#4224e9\"> 60</span>",
        "option_2": "<span style=\"color:#4224e9\"> 80</span>",
        "option_3": "<span style=\"color:#4224e9\"> 48</span>",
        "option_4": "<span style=\"color:#4224e9\"> 100</span>",
        "option_5": "",
        "answer": "2",
        "solution": "<br>https://appx-content-v2.classx.co.in/website/bulk_uploader_images/1750330267389_image008.png"
    },
    {
        "question": "<span>If A:B = 6 : 8 and B:C = 5 : 11, then A:B:C is:</span>",
        "option_1": "<span style=\"color:#4224e9\"> 15:20:44</span>",
        "option_2": "<span style=\"color:#4224e9\"> 14:31:25</span>",
        "option_3": "<span style=\"color:#4224e9\"> 15:32:44</span>",
        "option_4": "<span style=\"color:#4224e9\"> 11:23:14</span>",
        "option_5": "",
        "answer": "1",
        "solution": "<br>https://appx-content-v2.classx.co.in/website/bulk_uploader_images/1750330267389_image009.png"
    },
    {
        "question": "<span>In a room, there are some chairs and some people. If on each chair, only one person is seated, then there is no chair for exactly one person. If on each chair, two persons sit, then there is one vacant chair. What is the number of chairs in the room?</span>",
        "option_1": "<span style=\"color:#4224e9\"> 6</span>",
        "option_2": "<span style=\"color:#4224e9\"> 4</span>",
        "option_3": "<span style=\"color:#4224e9\"> 7</span>",
        "option_4": "<span style=\"color:#4224e9\"> 3</span>",
        "option_5": "",
        "answer": "4",
        "solution": "<br>https://appx-content-v2.classx.co.in/website/bulk_uploader_images/1750330267389_image010.png"
    },
    {
        "question": "<span>Aman has certain number of notes of denomination ₹20 and ₹10 which amount to ₹390. If the numbers of notes of each kind are interchanged, then the new amount is ₹90 less than before. Find the number of notes of ₹20 denomination.</span>",
        "option_1": "<span style=\"color:#4224e9\"> 15</span>",
        "option_2": "<span style=\"color:#4224e9\"> 12</span>",
        "option_3": "<span style=\"color:#4224e9\"> 16</span>",
        "option_4": "<span style=\"color:#4224e9\"> 14</span>",
        "option_5": "",
        "answer": "3",
        "solution": "<br>https://appx-content-v2.classx.co.in/website/bulk_uploader_images/1750330267389_image011.png"
    },
    {
        "question": "<span>If A:B = 6 : 8 and B:C = 5 : 12, then A:B:C is:</span>",
        "option_1": "<span style=\"color:#4224e9\"> 11:32:44</span>",
        "option_2": "<span style=\"color:#4224e9\"> 15:20:48</span>",
        "option_3": "<span style=\"color:#4224e9\"> 14:31:28</span>",
        "option_4": "<span style=\"color:#4224e9\"> 10:23:14</span>",
        "option_5": "",
        "answer": "2",
        "solution": "<br>https://appx-content-v2.classx.co.in/website/bulk_uploader_images/1750330267389_image012.png"
    },
    {
        "question": "<span>Find the mean proportional of 36 and 100.</span>",
        "option_1": "<span style=\"color:#4224e9\"> 70</span>",
        "option_2": "<span style=\"color:#4224e9\"> 60</span>",
        "option_3": "<span style=\"color:#4224e9\"> 55</span>",
        "option_4": "<span style=\"color:#4224e9\"> 65</span>",
        "option_5": "",
        "answer": "2",
        "solution": "<br>https://appx-content-v2.classx.co.in/website/bulk_uploader_images/1750330267389_image013.png"
    },
    {
        "question": "<span>In a garden, there are 6 daisy plants the first year. Each year, a gardener adds 3 new daisy plants. He has 26 jasmine plants the first year and loses 2 each year. When will the number of daisy plants equal to the number of jasmine plants after the first year?</span>",
        "option_1": "<span style=\"color:#4224e9\"> 2 </span>",
        "option_2": "<span style=\"color:#4224e9\"> 4 </span>",
        "option_3": "<span style=\"color:#4224e9\"> 5 </span>",
        "option_4": "<span style=\"color:#4224e9\"> 6 </span>",
        "option_5": "",
        "answer": "2",
        "solution": "<br>https://appx-content-v2.classx.co.in/website/bulk_uploader_images/1750330267389_image014.png"
    },
    {
        "question": "<span>Mrudula starts her job with a certain monthly salary and earns a fixed increment every year. If her salary was ₹28,400 after six years of service and ₹52,997 after fifteen years, find her annual increment.</span>",
        "option_1": "<span style=\"color:#4224e9\"> ₹12,002</span>",
        "option_2": "<span style=\"color:#4224e9\"> ₹1,824</span>",
        "option_3": "<span style=\"color:#4224e9\"> ₹2,733</span>",
        "option_4": "<span style=\"color:#4224e9\"> ₹1,200</span>",
        "option_5": "",
        "answer": "3",
        "solution": "<br>https://appx-content-v2.classx.co.in/website/bulk_uploader_images/1750330267389_image015.png"
    },
    {
        "question": "<p>R pays ₹100 to P with ₹5, ₹2 and ₹1 coins. The total number of coins used for paying are 40. What is the number of coins of denomination ₹5 in the payment?</p>",
        "option_1": "<p><span style=\"color:#4224e9\">16</span></p>",
        "option_2": "<p><span style=\"color:#4224e9\">18</span></p>",
        "option_3": "<p><span style=\"color:#4224e9\">17</span></p>",
        "option_4": "<p><span style=\"color:#4224e9\">13</span></p>",
        "option_5": "",
        "answer": "4",
        "solution": "<p>Let the number of coins of ₹5 = x</p> <p>number of coins of ₹2 = y</p> <p>number of coins of ₹1 = z</p> <p>ATQ,</p> <p>x + y + z = 40 ……….(1)</p> <p>5x + 2y + z = 100 ……….(2)</p> <p>Using option 3,</p> <p>when x = 13</p> <p>13 + y + z = 40 =&gt; y + z = 27 …………(3)</p> <p>5(13) + 2y + z = 100 =&gt; 2y + z = 35 ………….(4)</p> <p>subtract equation (3) from (4)</p> <p>2y – y = 35 – 27 =&gt; y = 8</p> <p>Put the value of y in equation (3)</p> <p>8 + z = 27 =&gt; z = 19</p> <p>Now, value of x, y &amp; z satisfy both the equations</p> <p>Verification:</p> <p>x + y + z = 40 =&gt; 13 + 8 + 19 = 40</p> <p>5x + 2y + z = 100 =&gt; 5(13) + 2(8) + 19 = 100</p>"
    },
    {
        "question": "<span>The mean proportional of </span><span> and </span><span> , where a is a positive number, is ____________ .</span><br>https://appx-content-v2.classx.co.in/website/bulk_uploader_images/1750330267389_image016.png<br>https://appx-content-v2.classx.co.in/website/bulk_uploader_images/1750330267389_image017.png",
        "option_1": "<span style=\"color:#4224e9\"> 12a</span><span style=\"line-height:115%;font-size:7.33pt;vertical-align:super;color:#4224e9\">2</span>",
        "option_2": "<br>https://appx-content-v2.classx.co.in/website/bulk_uploader_images/1750330267389_image020.png",
        "option_3": "<br>https://appx-content-v2.classx.co.in/website/bulk_uploader_images/1750330267389_image021.png",
        "option_4": "<span style=\"color:#4224e9\"> 12a</span>",
        "option_5": "",
        "answer": "3",
        "solution": "<br>https://appx-content-v2.classx.co.in/website/bulk_uploader_images/1750330267389_image022.png"
    },
    {
        "question": "<span>Each of Ravi and Kavita had some marbles. Kavita had 12 more marbles than Ravi had. If each of them had one more marble, then three times the number of marbles Kavita would then have had would have been equal to four times the number of marbles Ravi would then have had. How many marbles did Kavita actually have?</span>",
        "option_1": "<span style=\"color:#4224e9\"> 43</span>",
        "option_2": "<span style=\"color:#4224e9\"> 51</span>",
        "option_3": "<span style=\"color:#4224e9\"> 47</span>",
        "option_4": "<span style=\"color:#4224e9\"> 48</span>",
        "option_5": "",
        "answer": "3",
        "solution": "<br>https://appx-content-v2.classx.co.in/website/bulk_uploader_images/1750330267389_image023.png"
    },
    {
        "question": "<span>If the mean proportional between p and q is 12, then the possible values of p and q, respectively, are:</span>",
        "option_1": "<span style=\"color:#4224e9\"> 3, 38</span>",
        "option_2": "<span style=\"color:#4224e9\"> 24, 6</span>",
        "option_3": "<span style=\"color:#4224e9\"> 24, 16</span>",
        "option_4": "<span style=\"color:#4224e9\"> 3, 28</span>",
        "option_5": "",
        "answer": "2",
        "solution": "<br>https://appx-content-v2.classx.co.in/website/bulk_uploader_images/1750330267389_image024.png"
    },
    {
        "question": "<span>Find the fourth proportional to 4, 9 and 16.</span>",
        "option_1": "<span style=\"color:#4224e9\"> 27</span>",
        "option_2": "<span style=\"color:#4224e9\"> 36</span>",
        "option_3": "<span style=\"color:#4224e9\"> 18</span>",
        "option_4": "<span style=\"color:#4224e9\"> 16</span>",
        "option_5": "",
        "answer": "2",
        "solution": "<br>https://appx-content-v2.classx.co.in/website/bulk_uploader_images/1750330267389_image025.png"
    },
    {
        "question": "<span>30 is the mean proportional of 18 and A. Find the value of A.</span>",
        "option_1": "<span style=\"color:#4224e9\"> 40</span>",
        "option_2": "<span style=\"color:#4224e9\"> 45</span>",
        "option_3": "<span style=\"color:#4224e9\"> 60</span>",
        "option_4": "<span style=\"color:#4224e9\"> 50</span>",
        "option_5": "",
        "answer": "4",
        "solution": "<br>https://appx-content-v2.classx.co.in/website/bulk_uploader_images/1750330267389_image026.png"
    },
    {
        "question": "<span>Anna and Ben each have a collection of marbles. If Anna gives one marble to Ben, they will both have an equal number of marbles. Conversely, if Ben gives one marble to Anna, she will end up with three times the number of marbles that Ben has. What is the total number of marbles they both have?</span>",
        "option_1": "<span style=\"color:#4224e9\"> 11</span>",
        "option_2": "<span style=\"color:#4224e9\"> 8</span>",
        "option_3": "<span style=\"color:#4224e9\"> 10</span>",
        "option_4": "<span style=\"color:#4224e9\"> 9</span>",
        "option_5": "",
        "answer": "2",
        "solution": "<br>https://appx-content-v2.classx.co.in/website/bulk_uploader_images/1750330267389_image027.png"
    },
    {
        "question": "<span>The ratio between male and female members in a club is 2 : 3. If the number of male members is increased by 200, the ratio becomes 5 : 6. How many female members are there in the club?</span>",
        "option_1": "<span style=\"color:#4224e9\"> 1000</span>",
        "option_2": "<span style=\"color:#4224e9\"> 1200</span>",
        "option_3": "<span style=\"color:#4224e9\"> 1400</span>",
        "option_4": "<span style=\"color:#4224e9\"> 900</span>",
        "option_5": "",
        "answer": "2",
        "solution": "<br>https://appx-content-v2.classx.co.in/website/bulk_uploader_images/1750330267389_image028.png"
    },
    {
        "question": "<span>2 biscuits and 1 chocolate cost ₹69. 2 chocolates and 3 cups of coffee cost ₹127. 3 biscuits, 4 chocolates and 2 cups of coffee cost ₹229. Find the total cost (in ₹) of 5 biscuits, 5 chocolates and 5 cups of coffee.</span>",
        "option_1": "<span style=\"color:#4224e9\"> 304</span>",
        "option_2": "<span style=\"color:#4224e9\"> 345</span>",
        "option_3": "<span style=\"color:#4224e9\"> 375</span>",
        "option_4": "<span style=\"color:#4224e9\"> 355</span>",
        "option_5": "",
        "answer": "4",
        "solution": "<br>https://appx-content-v2.classx.co.in/website/bulk_uploader_images/1750330267389_image029.png"
    },
    {
        "question": "<span>Find the mean proportional of 12.96 and 0.16.</span>",
        "option_1": "<span style=\"color:#4224e9\"> 1.96</span>",
        "option_2": "<span style=\"color:#4224e9\"> 1.69</span>",
        "option_3": "<span style=\"color:#4224e9\"> 1.21</span>",
        "option_4": "<span style=\"color:#4224e9\"> 1.44</span>",
        "option_5": "",
        "answer": "4",
        "solution": "<br>https://appx-content-v2.classx.co.in/website/bulk_uploader_images/1750330267389_image030.png"
    },
    {
        "question": "<span>If A:B = 6 : 8 and B:C = 5 : 10, then A:B:C is:</span>",
        "option_1": "<span style=\"color:#4224e9\"> 1:3:4</span>",
        "option_2": "<span style=\"color:#4224e9\"> 1:2:4</span>",
        "option_3": "<span style=\"color:#4224e9\"> 4:3:2</span>",
        "option_4": "<span style=\"color:#4224e9\"> 3:4:8</span>",
        "option_5": "",
        "answer": "4",
        "solution": "<p><span>A : B : C = 30 : 40 : 80 = 3 : 4 : 8</span></p><p style=\"margin-top:0pt;margin-bottom:10pt\"></p><br>https://appx-content-v2.classx.co.in/website/bulk_uploader_images/1750330267389_image031.png<br>https://appx-content-v2.classx.co.in/website/bulk_uploader_images/1750330267389_image032.png"
    },
    {
        "question": "<span>The mean proportional of 2 and 32 is _____.</span>",
        "option_1": "<span style=\"color:#4224e9\"> 6</span>",
        "option_2": "<span style=\"color:#4224e9\"> 12</span>",
        "option_3": "<span style=\"color:#4224e9\"> 16</span>",
        "option_4": "<span style=\"color:#4224e9\"> 8</span>",
        "option_5": "",
        "answer": "4",
        "solution": "<span> Mean proportion = </span><br>https://appx-content-v2.classx.co.in/website/bulk_uploader_images/1750330267389_image033.png"
    },
    {
        "question": "<span>Raj divides ₹1,200 in the ratio 2 : 1 : 3 among three of his friends. The amount equal to the sum of three times the largest share and two times the smallest share is:</span>",
        "option_1": "<span style=\"color:#4224e9\"> ₹2,200</span>",
        "option_2": "<span style=\"color:#4224e9\"> ₹1,800</span>",
        "option_3": "<span style=\"color:#4224e9\"> ₹2,400</span>",
        "option_4": "<span style=\"color:#4224e9\"> ₹2,000</span>",
        "option_5": "",
        "answer": "1",
        "solution": "<br>https://appx-content-v2.classx.co.in/website/bulk_uploader_images/1750330267389_image034.png"
    },
    {
        "question": "<span>If 28.9 : x :: x : 36.1, and x &gt; 0, then find the value of x.</span>",
        "option_1": "<span style=\"color:#4224e9\"> 30.4</span>",
        "option_2": "<span style=\"color:#4224e9\"> 35</span>",
        "option_3": "<span style=\"color:#4224e9\"> 32.3</span>",
        "option_4": "<span style=\"color:#4224e9\"> 38.3</span>",
        "option_5": "",
        "answer": "3",
        "solution": "<br>https://appx-content-v2.classx.co.in/website/bulk_uploader_images/1750330267389_image035.png"
    },
    {
        "question": "<span>At a cafe, Rama bought drinks for her 7 friends at ₹240. Some of them wanted coffee, while others wanted black tea. A regular cup of coffee cost ₹40 and a regular cup of black tea cost ₹ 30. How many cups of tea did she purchase?</span>",
        "option_1": "<span style=\"color:#4224e9\"> 6</span>",
        "option_2": "<span style=\"color:#4224e9\"> 5</span>",
        "option_3": "<span style=\"color:#4224e9\"> 3</span>",
        "option_4": "<span style=\"color:#4224e9\"> 4</span>",
        "option_5": "",
        "answer": "4",
        "solution": "<br>https://appx-content-v2.classx.co.in/website/bulk_uploader_images/1750330267389_image036.png"
    },
    {
        "question": "<span>A payment of ₹120 is made with ₹10, ₹5 and ₹2 coins. A total of 25 coins are used. Which of the following is the number of ₹10 coins used in the payment?</span>",
        "option_1": "<span style=\"color:#4224e9\"> 8</span>",
        "option_2": "<span style=\"color:#4224e9\"> 6</span>",
        "option_3": "<span style=\"color:#4224e9\"> 10</span>",
        "option_4": "<span style=\"color:#4224e9\"> 4</span>",
        "option_5": "",
        "answer": "1",
        "solution": "<br>https://appx-content-v2.classx.co.in/website/bulk_uploader_images/1750330267389_image037.png"
    },
    {
        "question": "<span>The incomes of P, Q and R are in the ratio 10 : 12 : 9 and their expenditures are in the ratio 12 : 15 : 8. If Q saves 25% of his income, then what is the ratio of the savings of P, Q and R?</span>",
        "option_1": "<span style=\"color:#4224e9\"> 21 : 15 : 14</span>",
        "option_2": "<span style=\"color:#4224e9\"> 21 : 14 : 15</span>",
        "option_3": "<span style=\"color:#4224e9\"> 14 : 15 : 21</span>",
        "option_4": "<span style=\"color:#4224e9\"> 15 : 14 : 21</span>",
        "option_5": "",
        "answer": "3",
        "solution": "<br>https://appx-content-v2.classx.co.in/website/bulk_uploader_images/1750330267389_image038.png"
    },
    {
        "question": "<span>The monthly incomes of A, B and C are in the ratio 2 : 9 : 3 and their expenses are in the ratio 3 : 9 : 5. If A’s saving is half of his total income, then savings of A, B and C are, respectively, in the ratio of:</span>",
        "option_1": "<span style=\"color:#4224e9\"> 3 : 9 : 2</span>",
        "option_2": "<span style=\"color:#4224e9\"> 1 : 2 : 1</span>",
        "option_3": "<span style=\"color:#4224e9\"> 2 : 5 : 2</span>",
        "option_4": "<span style=\"color:#4224e9\"> 3 : 18 : 4</span>",
        "option_5": "",
        "answer": "4",
        "solution": "<br>https://appx-content-v2.classx.co.in/website/bulk_uploader_images/1750330267389_image039.png"
    },
    {
        "question": "<span>A money bag contains one rupee, 5 rupee and 10 rupee coins in the ratio of 3 : 5 : 7 respectively. If the total amount in the bag is ₹980,then find the number of coins of ₹10.</span>",
        "option_1": "<span style=\"color:#4224e9\"> 71</span>",
        "option_2": "<span style=\"color:#4224e9\"> 69</span>",
        "option_3": "<span style=\"color:#4224e9\"> 68</span>",
        "option_4": "<span style=\"color:#4224e9\"> 70</span>",
        "option_5": "",
        "answer": "4",
        "solution": "<br>https://appx-content-v2.classx.co.in/website/bulk_uploader_images/1750330267389_image040.png"
    },
    {
        "question": "<span>What is the ratio of the mean proportional of 1.21 and 0.09 with the mean proportional of 0.16 and 0.36?</span>",
        "option_1": "<span style=\"color:#4224e9\"> 11 : 8</span>",
        "option_2": "<span style=\"color:#4224e9\"> 13 : 8</span>",
        "option_3": "<span style=\"color:#4224e9\"> 11 : 13</span>",
        "option_4": "<span style=\"color:#4224e9\"> 13 : 12</span>",
        "option_5": "",
        "answer": "1",
        "solution": "<br>https://appx-content-v2.classx.co.in/website/bulk_uploader_images/1750330267389_image041.png"
    },
    {
        "question": "<span>The ratio of two numbers is 2 : 5 and their difference is 210. The smaller number is ____________.</span>",
        "option_1": "<span style=\"color:#4224e9\"> 350</span>",
        "option_2": "<span style=\"color:#4224e9\"> 150</span>",
        "option_3": "<span style=\"color:#4224e9\"> 60</span>",
        "option_4": "<span style=\"color:#4224e9\"> 140</span>",
        "option_5": "",
        "answer": "4",
        "solution": "<p style=\"margin-top:0pt;margin-bottom:10pt\"></p><p style=\"margin-top:0pt;margin-bottom:10pt;line-height:115%;font-size:18pt\"></p><br>https://appx-content-v2.classx.co.in/website/bulk_uploader_images/1750330267389_image042.png"
    }
]